seismicio/__init__.py
seismicio/Models/HeadersModel.py
seismicio/Models/InOutSuModel.py
seismicio/Models/SuDataModel.py
seismicio/Models/UtilsModel.py
seismicio/constants/HEADER_FORMAT_STRING.py
seismicio/constants/HEADER_KEYS.py
seismicio/constants/HEADER_KEYS_ALIASES.py
seismicio/constants/TRACE_HEADER_SIZE.py
seismicio/constants/__version__.py
seismicio/services/readsu.py
seismicio/services/readsuInMemory.py
seismicio/services/writesu.py
seismicio/services/writesuInMemory.py
seismicio-0.0.24.dist-info/LICENSE
seismicio-0.0.24.dist-info/METADATA
seismicio-0.0.24.dist-info/WHEEL
seismicio-0.0.24.dist-info/top_level.txt
seismicio-0.0.24.dist-info/RECORD
