Metadata-Version: 2.1
Name: seismicio
Version: 0.0.24
Summary: Read and write .su files for seismic data
Author: cadu-sg
Author-email: 
Keywords: python,io
Classifier: Development Status :: 1 - Planning
Classifier: Intended Audience :: Developers
Classifier: Programming Language :: Python :: 3
Classifier: Operating System :: Unix
Classifier: Operating System :: MacOS :: MacOS X
Classifier: Operating System :: Microsoft :: Windows
License-File: LICENSE
Requires-Dist: fs
Requires-Dist: numpy
